craftslicer/__init__.py
craftslicer/__main__.py
craftslicer/v2.py
craftslicer/core/__init__.py
craftslicer/core/model_processor.py
craftslicer/core/models.py
craftslicer/core/gl/__init__.py
craftslicer/core/gl/gl_elements.py
craftslicer/core/gl/gl_processor.py
craftslicer/core/gl/gl_shaders.py
craftslicer/core/gl/gl_widget.py
craftslicer/core/mc/__init__.py
craftslicer/core/mc/palette_creator.py
craftslicer/core/mc/palette_list.py
craftslicer/core/mc/one_dot_sixteen/__init__.py
craftslicer/core/mc/one_dot_sixteen/one_dot_sixteen.py
craftslicer/core/net/__init__.py
craftslicer/core/net/socket.py
craftslicer/core/qt/__init__.py
craftslicer/core/qt/qt_dialog.py
craftslicer/core/qt/qt_threads.py
craftslicer/core/qt/qt_widgets.py
craftslicer/core/res/__init__.py
craftslicer/core/res/qrc_resources.py
craftslicer/core/res/3d/statue.png
craftslicer/core/res/3d/statue.stl
CraftSlicer-2.0.dist-info/LICENSE
CraftSlicer-2.0.dist-info/METADATA
CraftSlicer-2.0.dist-info/WHEEL
CraftSlicer-2.0.dist-info/entry_points.txt
CraftSlicer-2.0.dist-info/top_level.txt
CraftSlicer-2.0.dist-info/RECORD
