Metadata-Version: 2.1
Name: CraftSlicer
Version: 2.0
Summary: A portal from reality to Minecraft
Home-page: https://github.com/ThatAquarel/CraftSlicer
Author: Aquarel
Author-email: flyingrobot910@gmail.com
License: MIT
Platform: UNKNOWN
Classifier: Development Status :: 4 - Beta
Classifier: Environment :: Win32 (MS Windows)
Classifier: Intended Audience :: End Users/Desktop
Classifier: License :: OSI Approved :: MIT License
Classifier: Natural Language :: English
Classifier: Programming Language :: Python :: 3 :: Only
Classifier: Programming Language :: Python :: 3.9
Classifier: Operating System :: OS Independent
Classifier: Topic :: Games/Entertainment
Requires-Dist: numpy
Requires-Dist: numpy-stl
Requires-Dist: pyrr
Requires-Dist: PyQt5
Requires-Dist: Pillow
Requires-Dist: nbt
Requires-Dist: trimesh
Requires-Dist: qdarkstyle
Requires-Dist: setuptools
Requires-Dist: PyOpenGl
